crypto_pay/__init__.py
crypto_pay/api.py
crypto_pay/crypto_pay.py
crypto_pay_api_cryptobot-1.0.3.dist-info/LICENSE
crypto_pay_api_cryptobot-1.0.3.dist-info/METADATA
crypto_pay_api_cryptobot-1.0.3.dist-info/WHEEL
crypto_pay_api_cryptobot-1.0.3.dist-info/top_level.txt
crypto_pay_api_cryptobot-1.0.3.dist-info/RECORD
