Metadata-Version: 2.1
Name: crypto_pay_api_cryptobot
Version: 1.0.3
Summary: A Python library for interacting with Crypto Pay API by CryptoBot
Home-page: https://github.com/ssheleg/crypto-pay-api-python
Author: sshlg
Author-email: sshlg93@gmail.com
Classifier: Programming Language :: Python :: 3
Classifier: License :: OSI Approved :: MIT License
Classifier: Operating System :: OS Independent
Requires-Python: >=3.6
License-File: LICENSE
Requires-Dist: requests
